boristool/__init__.py
boristool/_compat.py
boristool/commands.py
boristool/version.py
boristool/arch/__init__.py
boristool/arch/Darwin/__init__.py
boristool/arch/Darwin/df.py
boristool/arch/Darwin/system.py
boristool/arch/Linux/__init__.py
boristool/arch/Linux/df.py
boristool/arch/Linux/rpi.py
boristool/arch/generic/__init__.py
boristool/arch/generic/diskdevice.py
boristool/arch/generic/system.py
boristool/common/__init__.py
boristool/common/ack.py
boristool/common/action.py
boristool/common/borisspread.py
boristool/common/config.py
boristool/common/datacollect.py
boristool/common/definition.py
boristool/common/directive.py
boristool/common/history.py
boristool/common/log.py
boristool/common/parseconfig.py
boristool/common/sockets.py
boristool/common/timequeue.py
boristool/common/utils.py
boristool/common/actions/__init__.py
boristool/common/actions/notify.py
boristool/common/directives/__init__.py
boristool/common/directives/common.py
boristool/common/directives/disk.py
boristool/common/directives/rpi.py
boristool/tests/__init__.py
boristool/tests/env.py
boristool/tests/test.py
boristool/tests/test_arch_linux_rpi.py
boristool/tests/test_common_config.py
boristool/tests/test_common_timequeue.py
boristool/tests/test_common_utils.py
boristool-0.0.3.dist-info/DESCRIPTION.rst
boristool-0.0.3.dist-info/METADATA
boristool-0.0.3.dist-info/RECORD
boristool-0.0.3.dist-info/WHEEL
boristool-0.0.3.dist-info/entry_points.txt
boristool-0.0.3.dist-info/metadata.json
boristool-0.0.3.dist-info/top_level.txt
scripts/__init__.py
scripts/boris_agent.py
